izifile/__init__.py
izifile-0.1.0.dist-info/LICENSE
izifile-0.1.0.dist-info/WHEEL
izifile-0.1.0.dist-info/METADATA
izifile-0.1.0.dist-info/RECORD
